cartwright/CartwrightBase.py
cartwright/CategoryBases.py
cartwright/LSTM.py
cartwright/__init__.py
cartwright/analysis/__init__.py
cartwright/analysis/helpers.py
cartwright/analysis/space_resolution.py
cartwright/analysis/time_resolution.py
cartwright/categories/__init__.py
cartwright/categories/dates.py
cartwright/categories/geos.py
cartwright/categories/misc.py
cartwright/categories/partial_dates.py
cartwright/categories/timespans.py
cartwright/categorize.py
cartwright/category_helpers.py
cartwright/datasets/__init__.py
cartwright/datasets/fake_data.csv
cartwright/generate_training_data.py
cartwright/models/LSTM_RNN_Cartwright_v_0.0.1_dict.pth
cartwright/models/__init__.py
cartwright/py.typed
cartwright/resources/__init__.py
cartwright/resources/city.csv
cartwright/resources/city_lookup.csv
cartwright/resources/continent_lookup.csv
cartwright/resources/country_lookup.csv
cartwright/resources/states_provinces_lookup.csv
cartwright/schemas.py
cartwright/train_cartwright.py
cartwright/utils.py
cartwright-0.0.3.dist-info/entry_points.txt
cartwright-0.0.3.dist-info/LICENSE
cartwright-0.0.3.dist-info/WHEEL
cartwright-0.0.3.dist-info/METADATA
cartwright-0.0.3.dist-info/RECORD
