Metadata-Version: 2.1
Name: cartwright
Version: 0.0.3
Summary: A recurrent neural network paired with heuristic methods that automatically infer geospatial, temporal and feature columns
License: LGPL-3.0-or-later
Author: Kyle Marsh
Author-email: kyle@jataware.com
Requires-Python: >=3.7,<4.0
Classifier: License :: OSI Approved :: GNU Lesser General Public License v3 or later (LGPLv3+)
Classifier: Programming Language :: Python :: 3
Classifier: Programming Language :: Python :: 3.7
Classifier: Programming Language :: Python :: 3.8
Classifier: Programming Language :: Python :: 3.9
Classifier: Programming Language :: Python :: 3.10
Classifier: Programming Language :: Python :: 3.11
Requires-Dist: arrow (==1.0.3)
Requires-Dist: faker (>=14.0)
Requires-Dist: fuzzywuzzy (==0.18.0)
Requires-Dist: joblib (==1.0.1)
Requires-Dist: numpy (>=1.19)
Requires-Dist: pandas (>=1.1)
Requires-Dist: pydantic (==1.8.2)
Requires-Dist: python-levenshtein (==0.20.7)
Requires-Dist: scipy (>=1.5)
Requires-Dist: torch (>=1.8)
Requires-Dist: torchvision (>=0.9)
